torii_usb/__init__.py
torii_usb/full_devices.py
torii_usb/memory.py
torii_usb/py.typed
torii_usb/usb2.py
torii_usb/usb3.py
torii_usb/architecture/__init__.py
torii_usb/architecture/car.py
torii_usb/interface/__init__.py
torii_usb/interface/pipe.py
torii_usb/interface/ulpi.py
torii_usb/interface/utmi.py
torii_usb/interface/gateware_phy/__init__.py
torii_usb/interface/gateware_phy/phy.py
torii_usb/interface/gateware_phy/receiver.py
torii_usb/interface/gateware_phy/transmitter.py
torii_usb/interface/serdes_phy/__init__.py
torii_usb/interface/serdes_phy/ecp5.py
torii_usb/interface/serdes_phy/lfps.py
torii_usb/interface/serdes_phy/xc7.py
torii_usb/interface/serdes_phy/xc7_gtp.py
torii_usb/interface/serdes_phy/xc7_gtx.py
torii_usb/stream/__init__.py
torii_usb/stream/generator.py
torii_usb/test/__init__.py
torii_usb/test/usb2.py
torii_usb/test/utils.py
torii_usb/test/contrib/__init__.py
torii_usb/test/contrib/crc.py
torii_usb/test/contrib/usb_packet.py
torii_usb/usb/__init__.py
torii_usb/usb/device.py
torii_usb/usb/stream.py
torii_usb/usb/devices/__init__.py
torii_usb/usb/devices/acm.py
torii_usb/usb/request/__init__.py
torii_usb/usb/request/control.py
torii_usb/usb/request/interface.py
torii_usb/usb/request/standard.py
torii_usb/usb/request/windows/__init__.py
torii_usb/usb/request/windows/descriptorSet.py
torii_usb/usb/usb2/__init__.py
torii_usb/usb/usb2/control.py
torii_usb/usb/usb2/descriptor.py
torii_usb/usb/usb2/deserializer.py
torii_usb/usb/usb2/device.py
torii_usb/usb/usb2/endpoint.py
torii_usb/usb/usb2/packet.py
torii_usb/usb/usb2/request.py
torii_usb/usb/usb2/reset.py
torii_usb/usb/usb2/transfer.py
torii_usb/usb/usb2/endpoints/__init__.py
torii_usb/usb/usb2/endpoints/isochronous.py
torii_usb/usb/usb2/endpoints/status.py
torii_usb/usb/usb2/endpoints/stream.py
torii_usb/usb/usb2/interfaces/__init__.py
torii_usb/usb/usb3/__init__.py
torii_usb/usb/usb3/device.py
torii_usb/usb/usb3/application/__init__.py
torii_usb/usb/usb3/application/descriptor.py
torii_usb-0.8.1.dist-info/licenses/LICENSE
torii_usb-0.8.1.dist-info/licenses/LICENSE.docs
torii_usb-0.8.1.dist-info/METADATA
torii_usb-0.8.1.dist-info/WHEEL
torii_usb-0.8.1.dist-info/top_level.txt
torii_usb-0.8.1.dist-info/zip-safe
torii_usb-0.8.1.dist-info/RECORD
